gostcrypto/__init__.py
gostcrypto/gostcipher/__init__.py
gostcrypto/gostcipher/gost_34_12_2015.py
gostcrypto/gostcipher/gost_34_13_2015.py
gostcrypto/gosthash/__init__.py
gostcrypto/gosthash/gost_34_11_2012.py
gostcrypto/gosthmac/__init__.py
gostcrypto/gosthmac/r_50_1_113_2016.py
gostcrypto/gostoid/__init__.py
gostcrypto/gostoid/oid.py
gostcrypto/gostpbkdf/__init__.py
gostcrypto/gostpbkdf/r_50_1_111_2016.py
gostcrypto/gostrandom/__init__.py
gostcrypto/gostrandom/r_1323565_1_006_2017.py
gostcrypto/gostsignature/__init__.py
gostcrypto/gostsignature/gost_34_10_2012.py
gostcrypto/utils/__init__.py
gostcrypto/utils/utils.py
tests/__init__.py
tests/test_gostcipher.py
tests/test_gosthash.py
tests/test_gosthmac.py
tests/test_gostpbkdf.py
tests/test_gostrandom.py
tests/test_gostsignature.py
tests/test_oid.py
gostcrypto-1.2.5.dist-info/LICENSE
gostcrypto-1.2.5.dist-info/METADATA
gostcrypto-1.2.5.dist-info/WHEEL
gostcrypto-1.2.5.dist-info/top_level.txt
gostcrypto-1.2.5.dist-info/RECORD
