Metadata-Version: 1.2
Name: gostcrypto
Version: 1.2.5
Summary: GOST cryptographic functions
Home-page: https://github.com/drobotun/gostcrypto
Author: Evgeny Drobotun
Author-email: drobotun@xakep.ru
License: MIT
Project-URL: Documentation, https://gostcrypto.readthedocs.io/
Project-URL: Source, https://github.com/drobotun/gostcrypto
Keywords: cryptography,hash-functions,hmac,elliptic-curves,kuznechik,streebog,magma,block-cipher,cipher-algorithms,elliptic-curve-cryptography,pbkdf,gost-r-34-12-2015,gost-r-34-10-2012,gost-r-34-13-2015,gost-r-34-11-2012
Platform: UNKNOWN
Classifier: Development Status :: 4 - Beta
Classifier: Intended Audience :: Developers
Classifier: License :: OSI Approved :: MIT License
Classifier: Programming Language :: Python :: 3.6
Classifier: Programming Language :: Python :: 3.8
